sentry_quart/__init__.py
sentry_quart-0.1.0.dist-info/LICENSE
sentry_quart-0.1.0.dist-info/WHEEL
sentry_quart-0.1.0.dist-info/METADATA
sentry_quart-0.1.0.dist-info/RECORD
