Metadata-Version: 2.1
Name: sentry-quart
Version: 0.1.0
Summary: Sentry middleware for quart
Home-page: https://github.com/ponytailer/sentry-quart.git
License: MIT
Author: hs
Author-email: huangxiaohen2738@gmail.com
Requires-Python: >=3.7
Classifier: Environment :: Web Environment
Classifier: Intended Audience :: Developers
Classifier: License :: OSI Approved :: MIT License
Classifier: Programming Language :: Python
Classifier: Programming Language :: Python :: 3
Classifier: Programming Language :: Python :: 3.6
Classifier: Programming Language :: Python :: 3.7
Classifier: Programming Language :: Python :: 3.8
Classifier: Programming Language :: Python :: 3.9
Requires-Dist: sentry-sdk (>=1.3.0,<2.0.0)
Project-URL: Repository, https://github.com/ponytailer/sentry-quart.git
